{
    "uuid": [
        {
            "value": "cc51f5da-d449-4445-beea-3c74fc5e8411"
        }
    ],
    "langcode": [
        {
            "value": "en"
        }
    ],
    "uid": [
        {
            "target_type": "user",
            "target_uuid": "2f1d8340-8b1e-4065-89eb-ed179b103e00"
        }
    ],
    "filename": [
        {
            "value": "birth_0.jpg"
        }
    ],
    "uri": [
        {
            "value": "public:\/\/2021-12\/birth_0.jpg"
        }
    ],
    "filemime": [
        {
            "value": "image\/jpeg"
        }
    ],
    "filesize": [
        {
            "value": 31734
        }
    ],
    "status": [
        {
            "value": true
        }
    ],
    "created": [
        {
            "value": "2021-12-20T18:03:29+00:00",
            "format": "Y-m-d\\TH:i:sP"
        }
    ],
    "changed": [
        {
            "value": "2021-12-20T18:03:33+00:00",
            "format": "Y-m-d\\TH:i:sP"
        }
    ]
}